[
  {
    "type": "constructor",
    "inputs": [],
    "stateMutability": "nonpayable"
  },
  {
    "type": "function",
    "name": "data",
    "inputs": [
      {
        "name": "i",
        "type": "uint256",
        "internalType": "uint256"
      }
    ],
    "outputs": [
      {
        "name": "",
        "type": "string",
        "internalType": "string"
      }
    ],
    "stateMutability": "view"
  },
  {
    "type": "function",
    "name": "finalize",
    "inputs": [],
    "outputs": [],
    "stateMutability": "nonpayable"
  },
  {
    "type": "function",
    "name": "setPaths",
    "inputs": [
      {
        "name": "startIndex",
        "type": "uint256",
        "internalType": "uint256"
      },
      {
        "name": "paths",
        "type": "string[]",
        "internalType": "string[]"
      }
    ],
    "outputs": [],
    "stateMutability": "nonpayable"
  },
  {
    "type": "function",
    "name": "setSymbols",
    "inputs": [
      {
        "name": "quadrant",
        "type": "uint256",
        "internalType": "uint256"
      },
      {
        "name": "symbols",
        "type": "string[8]",
        "internalType": "string[8]"
      }
    ],
    "outputs": [],
    "stateMutability": "nonpayable"
  },
  {
    "type": "function",
    "name": "symbol",
    "inputs": [
      {
        "name": "quadrant",
        "type": "uint256",
        "internalType": "uint256"
      },
      {
        "name": "idx",
        "type": "uint8",
        "internalType": "uint8"
      }
    ],
    "outputs": [
      {
        "name": "",
        "type": "string",
        "internalType": "string"
      }
    ],
    "stateMutability": "view"
  },
  {
    "type": "error",
    "name": "AlreadyFinalized",
    "inputs": []
  },
  {
    "type": "error",
    "name": "IndexOutOfBounds",
    "inputs": []
  },
  {
    "type": "error",
    "name": "InvalidQuadrant",
    "inputs": []
  },
  {
    "type": "error",
    "name": "MaxBatch",
    "inputs": []
  },
  {
    "type": "error",
    "name": "OnlyCreator",
    "inputs": []
  }
]